{
    "configurations": [
        {
            "name": "Risc-V embed",
            "includePath": [
                "${workspaceFolder}/**",
                "~/ch32v/xpack-riscv-none-elf-gcc-12.2.0-3/lib/gcc/riscv-none-elf/12.2.0/include"
            ],
            "defines": [
                "SYSCLK_FREQ_144MHz"
            ],
            "compilerPath": "~/ch32v/xpack-riscv-none-elf-gcc-12.2.0-3/bin/riscv-none-elf-gcc",
            "cStandard": "c17",
            "cppStandard": "c++14",
            "intelliSenseMode": "linux-clang-x64",
            "compilerArgs": [
                "-march=rv32imafc -mabi=ilp32f -msmall-data-limit=8 -mno-save-restore -Os -fmessage-length=0 -fsigned-char -ffunction-sections -fdata-sections -Wunused -Wuninitialized  -g"
            ]
        }
    ],
    "version": 4
}